__init__.py
regression.py
linear_regression_sanaa-1.0.0.dist-info/LICENSE.txt
linear_regression_sanaa-1.0.0.dist-info/METADATA
linear_regression_sanaa-1.0.0.dist-info/WHEEL
linear_regression_sanaa-1.0.0.dist-info/top_level.txt
linear_regression_sanaa-1.0.0.dist-info/RECORD
