Metadata-Version: 2.1
Name: linear-regression-sanaa
Version: 1.0.0
Summary: An awesome package that does something
Home-page: http://pypi.python.org/pypi/linear-regression/
Author: sanaa bensaid
Author-email: s.bensaid@esi-sba.dz
License: LICENSE.txt
License-File: LICENSE.txt
